maestro/__init__.py
maestro/client.py
maestro/config_format.yaml
maestro/server.py
maestro/theme_format.yaml
maestro/control/__init__.py
maestro/control/commandmanager.py
maestro/control/configmanager.py
maestro/control/keyboardcontroller.py
maestro/control/maincontroller.py
maestro/model/__init__.py
maestro/model/application.py
maestro/model/collection.py
maestro/model/documentation.py
maestro/model/panels.py
maestro/sound/__init__.py
maestro/sound/songplayer.py
maestro/systemutils/__init__.py
maestro/systemutils/instance_control.py
maestro/systemutils/systemtools.py
maestro/themes/dark.yaml
maestro/themes/light.yaml
maestro/utils/__init__.py
maestro/utils/cache.py
maestro/utils/formatting.py
maestro/utils/loaders.py
maestro/utils/math.py
maestro/utils/parsing.py
maestro/utils/pointable_list.py
maestro/utils/ressources.py
maestro/view/__init__.py
maestro/view/album_panel.kv
maestro/view/appdocrender.py
maestro/view/application.py
maestro/view/collection_panel.kv
maestro/view/constants.py
maestro/view/doc_panel.kv
maestro/view/dummyview.py
maestro/view/maestro.kv
maestro/view/panel_common.kv
maestro/view/panels.py
maestro/view/queue_panel.kv
maestro/view/statusbar.kv
maestro/view/termdocrender.py
maestro/view/widgetutils.kv
maestro/view/widgetutils.py
maestro_music_player-0.1.0.dist-info/LICENSE
maestro_music_player-0.1.0.dist-info/METADATA
maestro_music_player-0.1.0.dist-info/WHEEL
maestro_music_player-0.1.0.dist-info/entry_points.txt
maestro_music_player-0.1.0.dist-info/top_level.txt
maestro_music_player-0.1.0.dist-info/RECORD
