Metadata-Version: 2.1
Name: maestro-music-player
Version: 0.1.0
Summary: A configurable and keyboard-centric music player
Home-page: https://framagit.org/Blaireau/maestro
Author: Baptiste Lambert
Author-email: rabbitstemplate <rabbitstemplate@disroot.org>
License: GNU GENERAL PUBLIC LICENSE
Project-URL: Repository, https://framagit.org/Blaireau/maestro
Keywords: audio,music player
Classifier: Programming Language :: Python :: 3
Classifier: License :: OSI Approved :: GNU General Public License v3 or later (GPLv3+)
Classifier: Operating System :: OS Independent
Classifier: Development Status :: 3 - Alpha
Classifier: Environment :: X11 Applications
Classifier: Intended Audience :: End Users/Desktop
Classifier: Operating System :: POSIX :: Linux
Classifier: Topic :: Multimedia :: Sound/Audio :: Players
Requires-Python: >=3.10
License-File: LICENSE
Requires-Dist: kivy
Requires-Dist: pyyaml
Requires-Dist: python-vlc
Requires-Dist: python-mpv
Requires-Dist: trio
Provides-Extra: test
Requires-Dist: pytest ; extra == 'test'
Requires-Dist: pytest-cov ; extra == 'test'
Requires-Dist: pytest-trio ; extra == 'test'
